application_profiles/__init__.py
application_profiles/application_profiles.py
application_profiles/application_profiles_enum.py
application_profiles/application_profiles_exception.py
application_profiles-0.2.0.dist-info/METADATA
application_profiles-0.2.0.dist-info/WHEEL
application_profiles-0.2.0.dist-info/RECORD
