Metadata-Version: 2.1
Name: application-profiles
Version: 0.2.0
Summary: This project brings (at least partially) the ability of providing properties files like Spring Framework but now in whatever Python context.
Home-page: https://github.com/diegosep/application-profiles
Author: Diego Sepulveda
Requires-Python: >=3.10,<4.0
Classifier: Programming Language :: Python :: 3
Classifier: Programming Language :: Python :: 3.10
Classifier: Programming Language :: Python :: 3.11
Classifier: Topic :: Software Development :: Libraries
Requires-Dist: pyyaml (>=6.0.1,<7.0.0)
Project-URL: Repository, https://github.com/diegosep/application-profiles
